dash_flows/AnimatedCircleNode.py
dash_flows/AnimatedNodeEdge.py
dash_flows/DashFlows.py
dash_flows/DevTools.py
dash_flows/ResizableNode.py
dash_flows/__init__.py
dash_flows/_imports_.py
dash_flows/dash_flows.min.js
dash_flows/dash_flows.min.js.map
dash_flows/metadata.json
dash_flows/package-info.json
dash_flows-0.0.4.dist-info/LICENSE
dash_flows-0.0.4.dist-info/METADATA
dash_flows-0.0.4.dist-info/WHEEL
dash_flows-0.0.4.dist-info/top_level.txt
dash_flows-0.0.4.dist-info/RECORD
