Metadata-Version: 2.2
Name: dash_flows
Version: 0.0.4
Summary: React Flow for the Plotly Dash framework with edittable handles.
Author: Pip Install Python <pipinstallpython@gmail.com>
License: MIT
Classifier: Framework :: Dash
License-File: LICENSE
Dynamic: author
Dynamic: classifier
Dynamic: description
Dynamic: description-content-type
Dynamic: license
Dynamic: summary
